{
    "applicationInstances":[
        {
            "applicationId":"app_boo",
            "clusterInstances":[
                {
                    "alias":"mytomcat",
                    "clusterId":"mytomcat.tomcat.domain",
                    "hostNames":[
                        "mytomcat.isuruh.lk"
                    ],
                    "instanceId":"app_boo-1",
                    "member":[
                        {
                            "clusterId":"mytomcat.tomcat.domain",
                            "memberId":"mytomcat.tomcat.domain5dd58649-0469-481e-a91e-75894069720c",
                            "memberIp":"10.0.0.5",
                            "memberPublicIp":"20.0.0.5",
                            "networkPartitionId":"openstack_R1",
                            "partitionId":"P1",
                            "property":[
                                {
                                    "name":"PRIMARY",
                                    "value":false
                                },
                                {
                                    "name":"MIN_COUNT",
                                    "value":1
                                }
                            ],
                            "serviceName":"tomcat",
                            "status":"Activated"
                        },
                        {
                            "clusterId":"mytomcat.tomcat.domain",
                            "memberId":"mytomcat.tomcat.domain368ebab7-f00e-4426-98e0-c929a0f1c6aa",
                            "memberIp":"10.0.0.10",
                            "memberPublicIp":"20.0.0.10",
                            "networkPartitionId":"openstack_R1",
                            "partitionId":"P1",
                            "property":[
                                {
                                    "name":"PRIMARY",
                                    "value":false
                                },
                                {
                                    "name":"MIN_COUNT",
                                    "value":1
                                }
                            ],
                            "serviceName":"tomcat",
                            "status":"Activated"
                        }
                    ],
                    "parentInstanceId":"app_boo-1",
                    "serviceName":"tomcat",
                    "status":"Active",
                    "tenantRange":"*"
                }
            ],
            "groupInstances":[
                {
                    "clusterInstances":[
                        {
                            "alias":"group8tom",
                            "clusterId":"group8tom.tomcat2.domain",
                            "hostNames":[
                                "group8tom.isuruh.lk"
                            ],
                            "instanceId":"app_boo-1",
                            "member":[
                                {
                                    "clusterId":"group8tom.tomcat2.domain",
                                    "memberId":"group8tom.tomcat2.domaine03864dc-d3b2-4417-adde-7ae8c76c72ca",
                                    "memberIp":"10.0.0.2",
                                    "memberPublicIp":"20.0.0.2",
                                    "networkPartitionId":"openstack_R1",
                                    "partitionId":"P1",
                                    "property":[
                                        {
                                            "name":"PRIMARY",
                                            "value":false
                                        },
                                        {
                                            "name":"MIN_COUNT",
                                            "value":1
                                        }
                                    ],
                                    "serviceName":"tomcat2",
                                    "status":"Activated"
                                },
                                {
                                    "clusterId":"group8tom.tomcat2.domain",
                                    "memberId":"group8tom.tomcat2.domainb0296d1a-4831-463a-b8a5-eae45fa9825d",
                                    "memberIp":"10.0.0.7",
                                    "memberPublicIp":"20.0.0.7",
                                    "networkPartitionId":"openstack_R1",
                                    "partitionId":"P1",
                                    "property":[
                                        {
                                            "name":"PRIMARY",
                                            "value":false
                                        },
                                        {
                                            "name":"MIN_COUNT",
                                            "value":1
                                        }
                                    ],
                                    "serviceName":"tomcat2",
                                    "status":"Activated"
                                }
                            ],
                            "parentInstanceId":"app_boo-1",
                            "serviceName":"tomcat2",
                            "status":"Active",
                            "tenantRange":"*"
                        }
                    ],
                    "groupId":"mygroup8",
                    "groupInstances":[
                        {
                            "clusterInstances":[
                                {
                                    "alias":"group9tom",
                                    "clusterId":"group9tom.tomcat1.domain",
                                    "hostNames":[
                                        "group9tom.isuruh.lk"
                                    ],
                                    "instanceId":"app_boo-1",
                                    "member":[
                                        {
                                            "clusterId":"group9tom.tomcat1.domain",
                                            "memberId":"group9tom.tomcat1.domain6dcd4cd8-1727-473d-83ff-30411050b37c",
                                            "memberIp":"10.0.0.1",
                                            "memberPublicIp":"20.0.0.1",
                                            "networkPartitionId":"openstack_R1",
                                            "partitionId":"P1",
                                            "property":[
                                                {
                                                    "name":"PRIMARY",
                                                    "value":false
                                                },
                                                {
                                                    "name":"MIN_COUNT",
                                                    "value":1
                                                }
                                            ],
                                            "serviceName":"tomcat1",
                                            "status":"Activated"
                                        },
                                        {
                                            "clusterId":"group9tom.tomcat1.domain",
                                            "memberId":"group9tom.tomcat1.domain199e4e9c-555b-4afc-a0dc-8cd277c9bf62",
                                            "memberIp":"10.0.0.6",
                                            "memberPublicIp":"20.0.0.6",
                                            "networkPartitionId":"openstack_R1",
                                            "partitionId":"P1",
                                            "property":[
                                                {
                                                    "name":"PRIMARY",
                                                    "value":false
                                                },
                                                {
                                                    "name":"MIN_COUNT",
                                                    "value":1
                                                }
                                            ],
                                            "serviceName":"tomcat1",
                                            "status":"Activated"
                                        }
                                    ],
                                    "parentInstanceId":"app_boo-1",
                                    "serviceName":"tomcat1",
                                    "status":"Active",
                                    "tenantRange":"*"
                                }
                            ],
                            "groupId":"mygroup9",
                            "instanceId":"app_boo-1",
                            "parentInstanceId":"app_boo-1",
                            "status":"Active"
                        },
                        {
                            "clusterInstances":[
                                {
                                    "alias":"group9tom",
                                    "clusterId":"group9tom.tomcat1.domain",
                                    "hostNames":[
                                        "group9tom.isuruh.lk"
                                    ],
                                    "instanceId":"app_boo-1",
                                    "member":[
                                        {
                                            "clusterId":"group9tom.tomcat1.domain",
                                            "memberId":"group9tom.tomcat1.domain6dcd4cd8-1727-473d-83ff-30411050b37c",
                                            "memberIp":"10.0.0.1",
                                            "memberPublicIp":"20.0.0.1",
                                            "networkPartitionId":"openstack_R1",
                                            "partitionId":"P1",
                                            "property":[
                                                {
                                                    "name":"PRIMARY",
                                                    "value":false
                                                },
                                                {
                                                    "name":"MIN_COUNT",
                                                    "value":1
                                                }
                                            ],
                                            "serviceName":"tomcat1",
                                            "status":"Activated"
                                        },
                                        {
                                            "clusterId":"group9tom.tomcat1.domain",
                                            "memberId":"group9tom.tomcat1.domain199e4e9c-555b-4afc-a0dc-8cd277c9bf62",
                                            "memberIp":"10.0.0.6",
                                            "memberPublicIp":"20.0.0.6",
                                            "networkPartitionId":"openstack_R1",
                                            "partitionId":"P1",
                                            "property":[
                                                {
                                                    "name":"PRIMARY",
                                                    "value":false
                                                },
                                                {
                                                    "name":"MIN_COUNT",
                                                    "value":1
                                                }
                                            ],
                                            "serviceName":"tomcat1",
                                            "status":"Activated"
                                        }
                                    ],
                                    "parentInstanceId":"app_boo-1",
                                    "serviceName":"tomcat1",
                                    "status":"Active",
                                    "tenantRange":"*"
                                }
                            ],
                            "groupId":"mygroup9-1",
                            "instanceId":"app_boo-1",
                            "parentInstanceId":"app_boo-1",
                            "status":"Active"
                        }
                    ],
                    "instanceId":"app_boo-1",
                    "parentInstanceId":"app_boo-1",
                    "status":"Active"
                },
                {
                    "clusterInstances":[
                        {
                            "alias":"group6tom",
                            "clusterId":"group6tom.tomcat2.domain",
                            "hostNames":[
                                "group6tom.isuruh.lk"
                            ],
                            "instanceId":"app_boo-1",
                            "member":[
                                {
                                    "clusterId":"group6tom.tomcat2.domain",
                                    "memberId":"group6tom.tomcat2.domaina178f042-416f-48c4-a0d6-d0792bee9232",
                                    "memberIp":"10.0.0.4",
                                    "memberPublicIp":"20.0.0.4",
                                    "networkPartitionId":"openstack_R1",
                                    "partitionId":"P1",
                                    "property":[
                                        {
                                            "name":"PRIMARY",
                                            "value":false
                                        },
                                        {
                                            "name":"MIN_COUNT",
                                            "value":1
                                        }
                                    ],
                                    "serviceName":"tomcat2",
                                    "status":"Activated"
                                },
                                {
                                    "clusterId":"group6tom.tomcat2.domain",
                                    "memberId":"group6tom.tomcat2.domain6eb8f988-fad5-4fe8-b3c5-e766f1831aef",
                                    "memberIp":"10.0.0.9",
                                    "memberPublicIp":"20.0.0.9",
                                    "networkPartitionId":"openstack_R1",
                                    "partitionId":"P1",
                                    "property":[
                                        {
                                            "name":"PRIMARY",
                                            "value":false
                                        },
                                        {
                                            "name":"MIN_COUNT",
                                            "value":1
                                        }
                                    ],
                                    "serviceName":"tomcat2",
                                    "status":"Activated"
                                }
                            ],
                            "parentInstanceId":"app_boo-1",
                            "serviceName":"tomcat2",
                            "status":"Active",
                            "tenantRange":"*"
                        }
                    ],
                    "groupId":"mygroup6",
                    "groupInstances":[
                        {
                            "clusterInstances":[
                                {
                                    "alias":"group7tom",
                                    "clusterId":"group7tom.tomcat1.domain",
                                    "hostNames":[
                                        "group7tom.isuruh.lk"
                                    ],
                                    "instanceId":"app_boo-1",
                                    "member":[
                                        {
                                            "clusterId":"group7tom.tomcat1.domain",
                                            "memberId":"group7tom.tomcat1.domain46df8a78-fb79-4698-a7d1-3a1cc3dac7b3",
                                            "memberIp":"10.0.0.3",
                                            "memberPublicIp":"20.0.0.3",
                                            "networkPartitionId":"openstack_R1",
                                            "partitionId":"P1",
                                            "property":[
                                                {
                                                    "name":"PRIMARY",
                                                    "value":false
                                                },
                                                {
                                                    "name":"MIN_COUNT",
                                                    "value":1
                                                }
                                            ],
                                            "serviceName":"tomcat1",
                                            "status":"Activated"
                                        },
                                        {
                                            "clusterId":"group7tom.tomcat1.domain",
                                            "memberId":"group7tom.tomcat1.domain88b8ff52-d6fd-49da-a556-b74eba27f046",
                                            "memberIp":"10.0.0.8",
                                            "memberPublicIp":"20.0.0.8",
                                            "networkPartitionId":"openstack_R1",
                                            "partitionId":"P1",
                                            "property":[
                                                {
                                                    "name":"PRIMARY",
                                                    "value":false
                                                },
                                                {
                                                    "name":"MIN_COUNT",
                                                    "value":1
                                                }
                                            ],
                                            "serviceName":"tomcat1",
                                            "status":"Activated"
                                        }
                                    ],
                                    "parentInstanceId":"app_boo-1",
                                    "serviceName":"tomcat1",
                                    "status":"Active",
                                    "tenantRange":"*"
                                }
                            ],
                            "groupId":"mygroup7",
                            "instanceId":"app_boo-1",
                            "parentInstanceId":"app_boo-1",
                            "status":"Active"
                        }
                    ],
                    "instanceId":"app_boo-1",
                    "parentInstanceId":"app_boo-1",
                    "status":"Active"
                }
            ],
            "instanceId":"app_boo-1",
            "status":"Active"
        },
        {
            "applicationId":"app_boo",
            "clusterInstances":[],
            "groupInstances":[],
            "instanceId":"app_boo-2",
            "status":"Active"
        }
    ],
    "id":"app_boo",
    "tenantAdminUsername":"admin",
    "tenantDomain":"carbon.super"
}